mwgencode_mcp/__init__.py
mwgencode_mcp/main.py
mwgencode_mcp/version.py
mwgencode_mcp-0.1.4.dist-info/METADATA
mwgencode_mcp-0.1.4.dist-info/WHEEL
mwgencode_mcp-0.1.4.dist-info/entry_points.txt
mwgencode_mcp-0.1.4.dist-info/top_level.txt
mwgencode_mcp-0.1.4.dist-info/RECORD
