Metadata-Version: 2.4
Name: mwgencode-mcp
Version: 0.1.4
Summary: A MCP-based code generation tool for web frameworks
Home-page: https://github.com/yourusername/mwgencode-mcp
Author: Your Name
Author-email: your.email@example.com
Classifier: Development Status :: 3 - Alpha
Classifier: Intended Audience :: Developers
Classifier: Topic :: Software Development :: Code Generators
Classifier: Programming Language :: Python :: 3
Classifier: Programming Language :: Python :: 3.8
Classifier: Programming Language :: Python :: 3.9
Classifier: Programming Language :: Python :: 3.10
Classifier: Programming Language :: Python :: 3.11
Classifier: License :: OSI Approved :: MIT License
Classifier: Operating System :: OS Independent
Requires-Python: >=3.11
Requires-Dist: mcp>=1.7.1
Requires-Dist: pyyaml>=6.0.2
Requires-Dist: mwgencode>=1.4.0
Requires-Dist: fastmcp>=2.2.10
Dynamic: author
Dynamic: author-email
Dynamic: classifier
Dynamic: description
Dynamic: description-content-type
Dynamic: home-page
Dynamic: requires-dist
Dynamic: requires-python
Dynamic: summary
